tailors_trainer/__init__.py
tailors_trainer/callbacks.py
tailors_trainer/cartographer.py
tailors_trainer/data.py
tailors_trainer/dataset_from_eb.py
tailors_trainer/domains.py
tailors_trainer/exceptions.py
tailors_trainer/optimizers.py
tailors_trainer/pefts.py
tailors_trainer/schedulers.py
tailors_trainer/train.py
tailors_trainer/trainer.py
tailors_trainer/agent/__init__.py
tailors_trainer/agent/agent.py
tailors_trainer/manager/__init__.py
tailors_trainer/manager/domains.py
tailors_trainer/manager/exceptions.py
tailors_trainer/manager/manager.py
tailors_trainer/manager/permissions.py
tailors_trainer/manager/apis/__init__.py
tailors_trainer/manager/apis/auths.py
tailors_trainer/manager/apis/passport_api.py
tailors_trainer/manager/apis/unsecure.py
tailors_trainer-0.1.4.dist-info/entry_points.txt
tailors_trainer-0.1.4.dist-info/LICENSE
tailors_trainer-0.1.4.dist-info/WHEEL
tailors_trainer-0.1.4.dist-info/METADATA
tailors_trainer-0.1.4.dist-info/RECORD
